README.rst
setup.py
Miniature.egg-info/PKG-INFO
Miniature.egg-info/SOURCES.txt
Miniature.egg-info/dependency_links.txt
Miniature.egg-info/requires.txt
Miniature.egg-info/top_level.txt
Miniature.egg-info/zip-safe
miniature/__init__.py
miniature/version.py
miniature/processor/__init__.py
miniature/processor/base.py
miniature/processor/pillow_processor.py
miniature/processor/wand_processor.py
miniature/thumbnails/__init__.py
miniature/thumbnails/base.py
miniature/thumbnails/conf.py
miniature/thumbnails/fields.py
miniature/thumbnails/files.py
miniature/thumbnails/templatetags/__init__.py
miniature/thumbnails/templatetags/miniature.py
test/__init__.py
test/test_processors.py